Metadata-Version: 2.1
Name: airbyte-source-braze
Version: 0.3.0
Summary: Source implementation for Braze.
Author: Airbyte
Author-email: contact@airbyte.io
Requires-Dist: airbyte-cdk
Provides-Extra: tests
Requires-Dist: requests-mock ~=1.9.3 ; extra == 'tests'
Requires-Dist: pytest ~=6.2 ; extra == 'tests'
Requires-Dist: pytest-mock ~=3.6.1 ; extra == 'tests'
